property_cached/__init__.py
property_cached/_version.txt
property_cached-1.6.3.dist-info/LICENSE
property_cached-1.6.3.dist-info/METADATA
property_cached-1.6.3.dist-info/WHEEL
property_cached-1.6.3.dist-info/top_level.txt
property_cached-1.6.3.dist-info/zip-safe
property_cached-1.6.3.dist-info/RECORD
