Metadata-Version: 2.1
Name: property-cached
Version: 1.6.3
Summary: A decorator for caching properties in classes (forked from cached-property).
Home-page: https://github.com/althonos/property-cached/
Author: Daniel Greenfeld
Author-email: pydanny@gmail.com
Maintainer: Martin Larralde
Maintainer-email: martin.larralde@ens-paris-saclay.fr
License: BSD
Keywords: cached-property,cache,property
Platform: any
Classifier: Development Status :: 5 - Production/Stable
Classifier: Intended Audience :: Developers
Classifier: License :: OSI Approved :: BSD License
Classifier: Natural Language :: English
Classifier: Operating System :: OS Independent
Classifier: Programming Language :: Python
Classifier: Programming Language :: Python :: 2
Classifier: Programming Language :: Python :: 2.7
Classifier: Programming Language :: Python :: 3
Classifier: Programming Language :: Python :: 3.4
Classifier: Programming Language :: Python :: 3.5
Classifier: Programming Language :: Python :: 3.6
Classifier: Programming Language :: Python :: 3.7
Requires-Python: >= 2.7, != 3.0.*, != 3.1.*, != 3.2.*, != 3.3.*
